add_return_None_to_init/__init__.py
add_return_None_to_init/_version.py
add_return_None_to_init-1.0.0.dist-info/LICENSE
add_return_None_to_init-1.0.0.dist-info/METADATA
add_return_None_to_init-1.0.0.dist-info/WHEEL
add_return_None_to_init-1.0.0.dist-info/entry_points.txt
add_return_None_to_init-1.0.0.dist-info/top_level.txt
add_return_None_to_init-1.0.0.dist-info/RECORD
